pyenvcheckr/__init__.py
pyenvcheckr/__main__.py
pyenvcheckr/checker.py
pyenvcheckr/cli.py
pyenvcheckr/version.py
pyenvcheckr-0.1.3.dist-info/licenses/LICENSE
pyenvcheckr-0.1.3.dist-info/METADATA
pyenvcheckr-0.1.3.dist-info/WHEEL
pyenvcheckr-0.1.3.dist-info/entry_points.txt
pyenvcheckr-0.1.3.dist-info/top_level.txt
pyenvcheckr-0.1.3.dist-info/RECORD
