Metadata-Version: 2.4
Name: pyenvcheckr
Version: 0.1.3
Summary: Check Python environment and validate dependencies from requirements.txt
Author-email: Abdullah Al Alif <alif126426@gmail.com>
License-Expression: MIT
Project-URL: Homepage, https://github.com/AbdullahAlAlif/envcheck
Project-URL: Documentation, https://github.com/AbdullahAlAlif/envcheck#readme
Project-URL: Repository, https://github.com/AbdullahAlAlif/envcheck.git
Project-URL: Issues, https://github.com/AbdullahAlAlif/envcheck/issues
Keywords: environment,dependencies,requirements,cli
Classifier: Development Status :: 3 - Alpha
Classifier: Intended Audience :: Developers
Classifier: Programming Language :: Python :: 3
Classifier: Programming Language :: Python :: 3.8
Classifier: Programming Language :: Python :: 3.9
Classifier: Programming Language :: Python :: 3.10
Classifier: Programming Language :: Python :: 3.11
Classifier: Programming Language :: Python :: 3.12
Classifier: Topic :: Software Development :: Libraries :: Python Modules
Classifier: Topic :: System :: Systems Administration
Requires-Python: >=3.8
License-File: LICENSE
Provides-Extra: dev
Requires-Dist: pytest>=7.0; extra == "dev"
Dynamic: license-file
